gha_timer/__init__.py
gha_timer/commands.py
gha_timer/config.py
gha_timer/enums.py
gha_timer/main.py
gha_timer/py.typed
gha_timer-1.1.0.dist-info/LICENSE
gha_timer-1.1.0.dist-info/METADATA
gha_timer-1.1.0.dist-info/WHEEL
gha_timer-1.1.0.dist-info/entry_points.txt
gha_timer-1.1.0.dist-info/RECORD
