Metadata-Version: 2.3
Name: gha_timer
Version: 1.1.0
Summary: Time and group logs for GitHub actions
License: MIT
Author: Nils Homer
Author-email: nils@fulcrumgenomics.com
Requires-Python: >=3.11
Classifier: Development Status :: 3 - Alpha
Classifier: Intended Audience :: Developers
Classifier: Intended Audience :: Science/Research
Classifier: License :: OSI Approved :: MIT License
Classifier: Natural Language :: English
Classifier: Operating System :: OS Independent
Classifier: Programming Language :: Python :: 3
Classifier: Programming Language :: Python :: 3.11
Classifier: Programming Language :: Python :: 3.12
Classifier: Programming Language :: Python :: 3.13
Classifier: Typing :: Typed
Requires-Dist: pyyaml (>=6.0.2,<7.0.0)
Requires-Dist: types-pyyaml (>=6.0.12.20241230,<7.0.0.0)
Project-URL: Bug Tracker, https://github.com/fulcrumgenomics/gha_timer/issues
Project-URL: Homepage, https://github.com/fulcrumgenomics/gha_timer
Project-URL: Repository, https://github.com/fulcrumgenomics/gha_timer
